{
  "ajax.cloudflare.com": {
    "hostname": "ajax.cloudflare.com",
    "firstPartyHostnames": [
      "www.symbolab.com"
    ],
    "firstParty": false,
    "cookies": [],
    "thirdParties": [],
    "CollectTime": "2020-05-27T14:12:12.819Z",
    "FirstRequestTime": "Wed, 27 May 2020 14:12:00 GMT",
    "LastRequestTime": "Invalid Date"
  },
  "ajax.googleapis.com": {
    "hostname": "ajax.googleapis.com",
    "firstPartyHostnames": [
      "www.symbolab.com"
    ],
    "firstParty": false,
    "cookies": [],
    "thirdParties": [],
    "CollectTime": "2020-05-27T14:12:12.819Z",
    "FirstRequestTime": "Wed, 27 May 2020 14:12:01 GMT",
    "LastRequestTime": "Invalid Date"
  },
  "fonts.googleapis.com": {
    "hostname": "fonts.googleapis.com",
    "firstPartyHostnames": [
      "www.symbolab.com"
    ],
    "firstParty": false,
    "cookies": [],
    "thirdParties": [],
    "CollectTime": "2020-05-27T14:12:12.819Z",
    "FirstRequestTime": "Wed, 27 May 2020 14:12:00 GMT",
    "LastRequestTime": "Invalid Date"
  },
  "fonts.gstatic.com": {
    "hostname": "fonts.gstatic.com",
    "firstPartyHostnames": [
      "www.symbolab.com"
    ],
    "firstParty": false,
    "cookies": [],
    "thirdParties": [],
    "CollectTime": "2020-05-27T14:12:12.819Z",
    "FirstRequestTime": "Wed, 27 May 2020 14:12:01 GMT",
    "LastRequestTime": "Wed, 27 May 2020 14:12:01 GMT"
  },
  "newtab": {
    "hostname": "newtab",
    "firstPartyHostnames": false,
    "firstParty": true,
    "cookies": "",
    "thirdParties": [
      "www.symbolab.com"
    ],
    "CollectTime": "2020-05-27T14:12:12.820Z",
    "FirstRequestTime": "Wed, 27 May 2020 14:11:57 GMT",
    "LastRequestTime": "Invalid Date"
  },
  "saved-work.desmos.com": {
    "hostname": "saved-work.desmos.com",
    "firstPartyHostnames": [
      "www.desmos.com"
    ],
    "firstParty": false,
    "cookies": [],
    "thirdParties": [],
    "CollectTime": "2020-05-27T14:12:12.820Z",
    "FirstRequestTime": "Wed, 27 May 2020 14:12:05 GMT",
    "LastRequestTime": "Wed, 27 May 2020 14:12:06 GMT"
  },
  "sessions.bugsnag.com": {
    "hostname": "sessions.bugsnag.com",
    "firstPartyHostnames": [
      "www.desmos.com"
    ],
    "firstParty": false,
    "cookies": [],
    "thirdParties": [],
    "CollectTime": "2020-05-27T14:12:12.820Z",
    "FirstRequestTime": "Wed, 27 May 2020 14:12:05 GMT",
    "LastRequestTime": "Invalid Date"
  },
  "www.desmos.com": {
    "hostname": "www.desmos.com",
    "firstPartyHostnames": [
      "www.symbolab.com"
    ],
    "firstParty": true,
    "cookies": "",
    "thirdParties": [
      "saved-work.desmos.com",
      "sessions.bugsnag.com"
    ],
    "CollectTime": "2020-05-27T14:12:12.820Z",
    "FirstRequestTime": "Wed, 27 May 2020 14:12:03 GMT",
    "LastRequestTime": "Wed, 27 May 2020 14:12:05 GMT"
  },
  "www.symbolab.com": {
    "hostname": "www.symbolab.com",
    "firstPartyHostnames": [
      "newtab"
    ],
    "firstParty": true,
    "cookies": "",
    "thirdParties": [
      "fonts.googleapis.com",
      "ajax.cloudflare.com",
      "fonts.gstatic.com",
      "ajax.googleapis.com",
      "www.desmos.com"
    ],
    "CollectTime": "2020-05-27T14:12:12.820Z",
    "FirstRequestTime": "Wed, 27 May 2020 14:12:00 GMT",
    "LastRequestTime": "Wed, 27 May 2020 14:12:01 GMT"
  }
}